danger_flake8/__init__.py
danger_flake8/plugin.py
danger_flake8/violation.py
danger_flake8-0.1.0.dist-info/LICENSE
danger_flake8-0.1.0.dist-info/WHEEL
danger_flake8-0.1.0.dist-info/METADATA
danger_flake8-0.1.0.dist-info/RECORD
